kronos_model_arch-0.1.0.dist-info/licenses/LICENSE
model/__init__.py
model/kronos.py
model/module.py
kronos_model_arch-0.1.0.dist-info/METADATA
kronos_model_arch-0.1.0.dist-info/WHEEL
kronos_model_arch-0.1.0.dist-info/top_level.txt
kronos_model_arch-0.1.0.dist-info/RECORD
