Metadata-Version: 2.4
Name: kronos-model-arch
Version: 0.1.0
Summary: Kronos: A Foundation Model for the Language of Financial Markets
Author: ShiYu
License-Expression: MIT
Project-URL: Homepage, https://github.com/shiyu-coder/Kronos
Project-URL: Documentation, https://github.com/shiyu-coder/Kronos
Project-URL: Repository, https://github.com/shiyu-coder/Kronos
Project-URL: Issues, https://github.com/shiyu-coder/Kronos/issues
Keywords: finance,trading,forecasting,transformer,machine-learning,financial-markets
Classifier: Development Status :: 4 - Beta
Classifier: Intended Audience :: Developers
Classifier: Intended Audience :: Financial and Insurance Industry
Classifier: Programming Language :: Python :: 3
Classifier: Programming Language :: Python :: 3.10
Classifier: Programming Language :: Python :: 3.11
Classifier: Programming Language :: Python :: 3.12
Classifier: Topic :: Scientific/Engineering :: Artificial Intelligence
Classifier: Topic :: Office/Business :: Financial
Requires-Python: >=3.10
License-File: LICENSE
Requires-Dist: numpy
Requires-Dist: pandas>=2.2.2
Requires-Dist: torch
Requires-Dist: einops==0.8.1
Requires-Dist: huggingface_hub==0.33.1
Requires-Dist: matplotlib==3.9.3
Requires-Dist: tqdm==4.67.1
Requires-Dist: safetensors==0.6.2
Dynamic: license-file
